touchless/gestures/__init__.py
touchless/gestures/clicks.py
touchless/gestures/fingers.py
touchless/gestures/geometry.py
touchless/gestures/hand.py
touchless/gestures/pinches.py
touchless/utils/events.py
touchless/utils/landmarks.py
touchless/utils/math_utils.py
touchless/utils/shapes.py
touchless-0.0.1.dist-info/LICENSE
touchless-0.0.1.dist-info/METADATA
touchless-0.0.1.dist-info/WHEEL
touchless-0.0.1.dist-info/top_level.txt
touchless-0.0.1.dist-info/RECORD
